{
  "id": "how-to/export/download-recommendations",
  "title": "Download Recommendations",
  "type": "how_to",
  "category": "development",
  "content": "# Download Recommendations\n\n## Available Guides\n* [Download Recommendations for an Asset](#download-recommendations-for-an-asset)\n\n**Reference:**\n\nField                | Description\n---------------------|------------------------------------------\nid | A unique random generated UUID as the key `id` for the Recommendation.\nsource | User, workload, Docker App or Kelvin SmartApp™ that created the Recommendation in KRN format. The KRN format is `krn:{nid}:{nss}`\nresource | Asset  in KRN format. The KRN format is `krn:asset:<asset_name>`\nstate | The current state of the Recommendation (`pending`, `accepted`, `rejected`, `applied`, `expired`, `error`)\ndescription | Detailed description of the Recommendation.\nactions | An array of objects with Control Change information. If the Recommendation is `pending`, it will display creation information or if the Recommendation is `accepted` or `applied` it will show the Control Change status. Each Control Change does not need to be related  to the `resource` of the Recommendation.\nconfidence | Confidence level of the Recommendation. This is usually, but not mandatory, related to any machine learning model confidence results.\ncreated | UTC time when the Recommendation was created, formatted in ISO 8601.\nupdated | UTC time when any Recommendation keys were last updated, formatted in ISO 8601.\npayload | New value to write to `resource`\nmetadata | Custom dictionary keys/values for use by clients for anything useful and related to the Recommendation.\nresource_parameters | Used for Internal use.\ntype | The Recommendation Type `name` associated with the Recommendation.\ntype_title |The Recommendation Type `title` of its `name` associated with the Recommendation.\nlogs | A date ordered list of the updates performed on this Recommendation.\n\n### Download Recommendations for an Asset\nIn this example we will get a list of all Recommendation for the Asset `pcp_01`.\n\n<div class=\"result\" markdown>\n\n=== \"Kelvin UI\"\n\n    You can download a range of Recommendation information from the Data Explorer page.\n\n    To do this go to the Data Explorer page.\n\n    \n\n    Select the Asset.\n\n    \n\n    Select one or more Data Streams that you want to download the related information.\n\n    \n\n    Choose a time period.\n\n    \n\n    Then click on the download button.\n\n    \n\n    Select the **Export Recommendations** option.\n\n    \n\n    And finally confirm the download by clicking on the **Okay** button.\n\n    \n\n=== \"Kelvin API\"\n\n    ```bash title=\"API cURL Example\" linenums=\"1\"\n    curl -X \"POST\" \\\n      \"https://<url.kelvin.ai>/api/v4/recommendations/range/get\" \\\n      -H \"Authorization: Bearer <Your Current Token>\" \\\n      -H \"Accept: application/json\" \\\n      -H \"Content-Type: application/json\" \\\n      -d '{\n            \"start_date\": \"2025-08-01T12:00:00.000000Z\",\n            \"end_date\": \"2025-08-02T12:00:00.000000Z\",\n            \"resources\": [\n                  \"krn:asset:pcp_01\"\n            ],\n            \"sources\": [\n                  \"krn:app:pcp-optimization\"\n            ],\n            \"states\": [],\n            \"types\": []\n         }'\n    ```\n\n    You will receive a response body with a status code of 200, indicating a successful operation. For example, the response body might look like this:\n\n    ```json title=\"API cURL Example Response\" linenums=\"1\"\n    {\n      \"pagination\": {\n        \"next_page\": \"W3siS2V5IjoiaWQiLCJWYWx1ZSI6IjM2NWFlNGU0LWZiMGItNGJhZS1iODcxLTBkMjk4YTZjN2I1NCJ9XQ==\",\n        \"previous_page\": null\n      },\n      \"data\": [\n        {\n          \"id\": \"0190466b-5540-40cc-990b-7ca580139a20\",\n          \"source\": \"krn:wlappv:sales-01-cluster/pcp-optimization-d2tmv6s14vzz:pcp-optimization/1.0.202403041506\",\n          \"resource\": \"krn:asset:pcp_01\",\n          \"state\": \"auto_accepted\",\n          \"description\": \"Casing Pressure Event Detected, no changes allowed\",\n          \"actions\": {},\n          \"created\": \"2025-08-02T11:59:51.213148Z\",\n          \"updated\": \"2025-08-02T11:59:51.213148Z\",\n          \"expiration_date\": \"2025-08-02T19:59:46.788691Z\",\n          \"metadata\": {},\n          \"resource_parameters\": {\n            \"dd_rate_max\": 123,\n            \"dd_rate_min\": 0.1,\n            \"faulty_gauge\": false,\n            \"kelvin_control_mode\": \"Closed\",\n            \"lock_mode\": false\n          },\n          \"type\": \"no_action\",\n          \"type_title\": \"No Action\",\n          \"logs\": [\n            {\n              \"source\": \"krn:wlappv:sales-01-cluster/pcp-optimization-d2tmv6s14vzz:pcp-optimization/1.0.202403041506\",\n              \"state\": \"auto_accepted\",\n              \"created_at\": \"2025-08-02T11:59:51.213148Z\"\n            }\n          ]\n        },  \n        {\n          \"id\": \"03c9f4aa-b302-4c3e-8371-92e8dd03d606\",\n          \"source\": \"krn:wlappv:sales-01-cluster/pcp-optimization-d2tmv6s14vzz:pcp-optimization/1.0.202403041506\",\n          \"resource\": \"krn:asset:pcp_01\",\n          \"state\": \"auto_accepted\",\n          \"description\": \"Above max Drawdown, parameters stable\",\n          \"actions\": {},\n          \"created\": \"2025-08-02T00:44:46.356244Z\",\n          \"updated\": \"2025-08-02T00:44:46.356244Z\",\n          \"expiration_date\": \"2025-08-02T08:44:38.724014Z\",\n          \"metadata\": {},\n          \"resource_parameters\": {\n            \"dd_rate_max\": 123,\n            \"dd_rate_min\": 0.1,\n            \"faulty_gauge\": false,\n            \"kelvin_control_mode\": \"Closed\",\n            \"lock_mode\": false\n          },\n          \"type\": \"no_action\",\n          \"type_title\": \"No Action\",\n          \"logs\": [\n            {\n              \"source\": \"krn:wlappv:sales-01-cluster/pcp-optimization-d2tmv6s14vzz:pcp-optimization/1.0.202403041506\",\n              \"state\": \"auto_accepted\",\n              \"created_at\": \"2025-08-02T00:44:46.356244Z\"\n            }\n          ]\n        }\n      ]\n    }\n    ```\n\n=== \"Kelvin API Client (Python)\"\n\n    ```python title=\"API Client (Python) Example\" linenums=\"1\"\n    from kelvin.api.client import Client\n\n    # Login\n    client = Client(url=\"https://<url.kelvin.ai>\", username=\"<your_username>\")\n    client.login(password=\"<your_password>\")\n\n    # Get Range of Recommendations\n    response = client.recommendation.get_recommendation_range(\n       data={\n          \"start_date\": \"2025-08-01T12:00:00.000000Z\",\n          \"end_date\": \"2025-08-02T12:00:00.000000Z\",\n          \"resources\": [\n                \"krn:asset:pcp_01\",\n          ],\n          \"sources\": [\n                \"krn:app:pcp-optimization\",\n          ],\n          \"states\": [],\n          \"types\": [],\n       }\n    )\n\n    # Convert the response into a Pandas DataFrame\n    df = response.to_df()\n    df = df[[\"type\", \"state\", \"resource\", \"description\"]] \n\n    # Print the result\n    print(df)\n    ```\n\n    The response file will look something like this;\n\n    ```bash title=\"API Client (Python) Example Response\" linenums=\"1\"\n                type          state          resource\n    0       no_action  auto_accepted  krn:asset:pcp_01\n    1       no_action  auto_accepted  krn:asset:pcp_01\n    2  speed_decrease  auto_accepted  krn:asset:pcp_01\n    3       no_action  auto_accepted  krn:asset:pcp_01\n    4       no_action  auto_accepted  krn:asset:pcp_01\n    ```\n\n</div>",
  "summary": "",
  "source": "core-docs/docs/developer-tools/how-to/export/download-recommendations.md",
  "code_examples": [
    {
      "language": "bash",
      "code": "curl -X \"POST\" \\\n      \"https://<url.kelvin.ai>/api/v4/recommendations/range/get\" \\\n      -H \"Authorization: Bearer <Your Current Token>\" \\\n      -H \"Accept: application/json\" \\\n      -H \"Content-Type: application/json\" \\\n      -d '{\n            \"start_date\": \"2025-08-01T12:00:00.000000Z\",\n            \"end_date\": \"2025-08-02T12:00:00.000000Z\",\n            \"resources\": [\n                  \"krn:asset:pcp_01\"\n            ],\n            \"sources\": [\n                  \"krn:app:pcp-optimization\"\n            ],\n            \"states\": [],\n            \"types\": []\n         }'",
      "title": "API cURL Example"
    },
    {
      "language": "json",
      "code": "{\n      \"pagination\": {\n        \"next_page\": \"W3siS2V5IjoiaWQiLCJWYWx1ZSI6IjM2NWFlNGU0LWZiMGItNGJhZS1iODcxLTBkMjk4YTZjN2I1NCJ9XQ==\",\n        \"previous_page\": null\n      },\n      \"data\": [\n        {\n          \"id\": \"0190466b-5540-40cc-990b-7ca580139a20\",\n          \"source\": \"krn:wlappv:sales-01-cluster/pcp-optimization-d2tmv6s14vzz:pcp-optimization/1.0.202403041506\",\n          \"resource\": \"krn:asset:pcp_01\",\n          \"state\": \"auto_accepted\",\n          \"description\": \"Casing Pressure Event Detected, no changes allowed\",\n          \"actions\": {},\n          \"created\": \"2025-08-02T11:59:51.213148Z\",\n          \"updated\": \"2025-08-02T11:59:51.213148Z\",\n          \"expiration_date\": \"2025-08-02T19:59:46.788691Z\",\n          \"metadata\": {},\n          \"resource_parameters\": {\n            \"dd_rate_max\": 123,\n            \"dd_rate_min\": 0.1,\n            \"faulty_gauge\": false,\n            \"kelvin_control_mode\": \"Closed\",\n            \"lock_mode\": false\n          },\n          \"type\": \"no_action\",\n          \"type_title\": \"No Action\",\n          \"logs\": [\n            {\n              \"source\": \"krn:wlappv:sales-01-cluster/pcp-optimization-d2tmv6s14vzz:pcp-optimization/1.0.202403041506\",\n              \"state\": \"auto_accepted\",\n              \"created_at\": \"2025-08-02T11:59:51.213148Z\"\n            }\n          ]\n        },  \n        {\n          \"id\": \"03c9f4aa-b302-4c3e-8371-92e8dd03d606\",\n          \"source\": \"krn:wlappv:sales-01-cluster/pcp-optimization-d2tmv6s14vzz:pcp-optimization/1.0.202403041506\",\n          \"resource\": \"krn:asset:pcp_01\",\n          \"state\": \"auto_accepted\",\n          \"description\": \"Above max Drawdown, parameters stable\",\n          \"actions\": {},\n          \"created\": \"2025-08-02T00:44:46.356244Z\",\n          \"updated\": \"2025-08-02T00:44:46.356244Z\",\n          \"expiration_date\": \"2025-08-02T08:44:38.724014Z\",\n          \"metadata\": {},\n          \"resource_parameters\": {\n            \"dd_rate_max\": 123,\n            \"dd_rate_min\": 0.1,\n            \"faulty_gauge\": false,\n            \"kelvin_control_mode\": \"Closed\",\n            \"lock_mode\": false\n          },\n          \"type\": \"no_action\",\n          \"type_title\": \"No Action\",\n          \"logs\": [\n            {\n              \"source\": \"krn:wlappv:sales-01-cluster/pcp-optimization-d2tmv6s14vzz:pcp-optimization/1.0.202403041506\",\n              \"state\": \"auto_accepted\",\n              \"created_at\": \"2025-08-02T00:44:46.356244Z\"\n            }\n          ]\n        }\n      ]\n    }",
      "title": "API cURL Example Response"
    },
    {
      "language": "python",
      "code": "from kelvin.api.client import Client\n\n    # Login\n    client = Client(url=\"https://<url.kelvin.ai>\", username=\"<your_username>\")\n    client.login(password=\"<your_password>\")\n\n    # Get Range of Recommendations\n    response = client.recommendation.get_recommendation_range(\n       data={\n          \"start_date\": \"2025-08-01T12:00:00.000000Z\",\n          \"end_date\": \"2025-08-02T12:00:00.000000Z\",\n          \"resources\": [\n                \"krn:asset:pcp_01\",\n          ],\n          \"sources\": [\n                \"krn:app:pcp-optimization\",\n          ],\n          \"states\": [],\n          \"types\": [],\n       }\n    )\n\n    # Convert the response into a Pandas DataFrame\n    df = response.to_df()\n    df = df[[\"type\", \"state\", \"resource\", \"description\"]] \n\n    # Print the result\n    print(df)",
      "title": "API Client (Python) Example"
    },
    {
      "language": "bash",
      "code": "type          state          resource\n    0       no_action  auto_accepted  krn:asset:pcp_01\n    1       no_action  auto_accepted  krn:asset:pcp_01\n    2  speed_decrease  auto_accepted  krn:asset:pcp_01\n    3       no_action  auto_accepted  krn:asset:pcp_01\n    4       no_action  auto_accepted  krn:asset:pcp_01",
      "title": "API Client (Python) Example Response"
    }
  ],
  "related": [],
  "tags": [
    "api",
    "cli",
    "create",
    "development",
    "docker",
    "download",
    "monitor",
    "recommendations",
    "sdk",
    "smartapp"
  ],
  "metadata": {
    "subcategory": "developer-tools",
    "steps": [],
    "step_count": 0,
    "last_updated": "2026-02-04"
  }
}