{
  "id": "sdk/api-client/client.model.requests/workloadsstart",
  "title": "WorkloadsStart",
  "type": "sdk_class",
  "category": "sdk",
  "content": "# WorkloadsStart\n\nInherits from: WorkloadNamesList\n\n\nWorkloadsStart object.\n\nParameters\n----------\n",
  "summary": "WorkloadsStart object.",
  "source": "api/src/kelvin/api/client/model/requests.py",
  "code_examples": [
    {
      "language": "python",
      "code": "from kelvin.api import Client\n\nclient = Client()\nresult = client.client.model.requests.method()"
    }
  ],
  "related": [
    "sdk/api-client"
  ],
  "tags": [
    "api-client",
    "sdk",
    "python",
    "class"
  ],
  "metadata": {
    "package": "api-client",
    "module": "client.model.requests",
    "item_type": "class",
    "methods": [],
    "last_updated": "2026-02-04"
  }
}